MANIFEST.in
README.rst
setup.cfg
setup.py
bin/pfdcm
pfdcm/__init__.py
pfdcm/pfdcm.py
pfdcm/pfstorage.py
pfdcm.egg-info/PKG-INFO
pfdcm.egg-info/SOURCES.txt
pfdcm.egg-info/dependency_links.txt
pfdcm.egg-info/not-zip-safe
pfdcm.egg-info/requires.txt
pfdcm.egg-info/top_level.txt