Metadata-Version: 1.0
Name: pfdcm
Version: 2.0.2.6
Summary: Path and File DICOM
Home-page: https://github.com/FNNDSC/pfcon
Author: Rudolph Pienaar
Author-email: rudolph.pienaar@gmail.com
License: MIT
Platform: UNKNOWN
